LICENSE.txt
MANIFEST.in
README.rst
requirements.txt
setup.py
ioos_qartod/__init__.py
ioos_qartod.egg-info/PKG-INFO
ioos_qartod.egg-info/SOURCES.txt
ioos_qartod.egg-info/dependency_links.txt
ioos_qartod.egg-info/requires.txt
ioos_qartod.egg-info/top_level.txt
ioos_qartod/qc_tests/__init__.py
ioos_qartod/qc_tests/auxillary_checks.py
ioos_qartod/qc_tests/gliders.py
ioos_qartod/qc_tests/qc.py
test/__init__.py
test/test_auxillary_checks.py
test/test_glider_checks.py
test/test_qartod_qc.py