Metadata-Version: 1.1
Name: ioos-qartod
Version: 0.0.3
Summary: IOOS QARTOD Tests implemented in Python
Home-page: https://github.com/asascience-open/QARTOD
Author: Ben Adams
Author-email: BAdams@asascience.com
License: Apache License
